async_geotiff/__init__.py
async_geotiff/_array.py
async_geotiff/_crs.py
async_geotiff/_fetch.py
async_geotiff/_geotiff.py
async_geotiff/_ifd.py
async_geotiff/_overview.py
async_geotiff/_transform.py
async_geotiff/_version.py
async_geotiff/enums.py
async_geotiff/py.typed
async_geotiff/tms.py
async_geotiff-0.1.0b4.dist-info/licenses/LICENSE
async_geotiff-0.1.0b4.dist-info/WHEEL
async_geotiff-0.1.0b4.dist-info/METADATA
async_geotiff-0.1.0b4.dist-info/RECORD
