Metadata-Version: 2.4
Name: async-geotiff
Version: 0.1.0b4
Summary: Async GeoTIFF reader for Python
Keywords: geotiff,tiff,async,cog,raster,gis
Author: Kyle Barron
Author-email: Kyle Barron <kyle@developmentseed.org>
License-Expression: MIT
License-File: LICENSE
Classifier: Development Status :: 3 - Alpha
Classifier: Intended Audience :: Developers
Classifier: License :: OSI Approved :: MIT License
Classifier: Programming Language :: Python :: 3
Classifier: Programming Language :: Python :: 3.11
Classifier: Programming Language :: Python :: 3.12
Classifier: Programming Language :: Python :: 3.13
Classifier: Programming Language :: Python :: 3.14
Classifier: Topic :: Scientific/Engineering :: GIS
Classifier: Typing :: Typed
Requires-Dist: affine>=2.4.0
Requires-Dist: async-tiff>=0.5.0b1
Requires-Dist: numpy>=2.0
Requires-Dist: pyproj>=3.3.0
Requires-Dist: morecantile>=7.0,<8.0 ; extra == 'morecantile'
Requires-Python: >=3.11
Project-URL: Changelog, https://github.com/developmentseed/async-geotiff/blob/main/CHANGELOG.md
Project-URL: Documentation, https://developmentseed.github.io/async-geotiff/
Project-URL: Homepage, https://github.com/developmentseed/async-geotiff
Project-URL: Issues, https://github.com/developmentseed/async-geotiff/issues
Project-URL: Repository, https://github.com/developmentseed/async-geotiff
Provides-Extra: morecantile
